{
  "routes": [
    {
      "method": "GET",
      "path": "/offices",
      "handler": "offices.find",
      "config": {
        "policies": []
      }
    },
    {
      "method": "GET",
      "path": "/offices/count",
      "handler": "offices.count",
      "config": {
        "policies": []
      }
    },
    {
      "method": "GET",
      "path": "/offices/:id",
      "handler": "offices.findOne",
      "config": {
        "policies": []
      }
    },
    {
      "method": "POST",
      "path": "/offices",
      "handler": "offices.create",
      "config": {
        "policies": []
      }
    },
    {
      "method": "PUT",
      "path": "/offices/:id",
      "handler": "offices.update",
      "config": {
        "policies": []
      }
    },
    {
      "method": "DELETE",
      "path": "/offices/:id",
      "handler": "offices.delete",
      "config": {
        "policies": []
      }
    }
  ]
}
